interaction/__init__.py
interaction/gesture/__init__.py
interaction/gesture/actions.py
interaction/gesture/calculations.py
interaction/gesture/drag_and_drop.py
interaction/gesture/enums.py
interaction/gesture/exceptions.py
interaction/gesture/pinch.py
interaction/gesture/swipe.py
interaction.gesture.actions-0.3.0.dist-info/LICENSE
interaction.gesture.actions-0.3.0.dist-info/METADATA
interaction.gesture.actions-0.3.0.dist-info/WHEEL
interaction.gesture.actions-0.3.0.dist-info/top_level.txt
interaction.gesture.actions-0.3.0.dist-info/RECORD
