Metadata-Version: 2.1
Name: interaction.gesture.actions
Version: 0.3.0
Summary: Gesture actions library for Appium
Project-URL: homepage, https://github.com/tanakrit-d/appium-gesture-actions
Project-URL: repository, https://github.com/tanakrit-d/appium-gesture-actions
Project-URL: issues, https://github.com/tanakrit-d/appium-gesture-actions/issues
Keywords: appium,actions,gestures,swipe,scroll,pinch,zoom,drag and drop
Classifier: Programming Language :: Python :: 3
Classifier: License :: OSI Approved :: MIT License
Classifier: Operating System :: OS Independent
Requires-Python: >=3.9
License-File: LICENSE
Requires-Dist: appium-python-client>=4.3.0
Requires-Dist: selenium>=4.26.1
